robots/__init__.py
robots/robo_base.py
robots/robo_lutador.py
robots/robo_medico.py
robot_fight_package-0.0.1.dist-info/METADATA
robot_fight_package-0.0.1.dist-info/WHEEL
robot_fight_package-0.0.1.dist-info/top_level.txt
robot_fight_package-0.0.1.dist-info/RECORD
