Metadata-Version: 2.4
Name: robot-fight-package
Version: 0.0.1
Summary: Simulação de combate entre robôs lutadores
Home-page: https://github.com/Draky-Rollgard/Robot_Fight
Author: Cleiton
Author-email: cleitonguilhermite@gmail.com
Requires-Python: >=3.12.9
Dynamic: author
Dynamic: author-email
Dynamic: description
Dynamic: description-content-type
Dynamic: home-page
Dynamic: requires-python
Dynamic: summary
